Metadata-Version: 2.1
Name: python-games
Version: 1.0.4
Summary: A python package with different python games
Home-page: https://github.com/kevys/python-games
Author: Kevys
License: MIT
Project-URL: Issues, https://github.com/kevys/python-games/issues
Keywords: python
Platform: UNKNOWN
Classifier: Programming Language :: Python :: 3
Classifier: Operating System :: OS Independent
Requires-Python: >=3.8.0
License-File: LICENSE
